Metadata-Version: 2.1
Name: iters.py
Version: 0.7.0
Summary: Rich Iterators for Python.
Home-page: https://github.com/nekitdev/iters.py
Author: nekitdev
Author-email: nekitdevofficial@gmail.com
License: MIT
Project-URL: Issue tracker, https://github.com/nekitdev/iters.py/issues
Platform: UNKNOWN
Classifier: Development Status :: 4 - Beta
Classifier: License :: OSI Approved :: MIT License
Classifier: Programming Language :: Python :: 3.6
Classifier: Programming Language :: Python :: 3.7
Classifier: Programming Language :: Python :: 3.8
Classifier: Programming Language :: Python :: 3.9
Classifier: Natural Language :: English
Classifier: Operating System :: OS Independent
Requires-Python: >=3.6
